ph.py
phlib.py
phlib-0.1.1.dist-info/DESCRIPTION.rst
phlib-0.1.1.dist-info/METADATA
phlib-0.1.1.dist-info/RECORD
phlib-0.1.1.dist-info/WHEEL
phlib-0.1.1.dist-info/entry_points.txt
phlib-0.1.1.dist-info/metadata.json
phlib-0.1.1.dist-info/top_level.txt
