Metadata-Version: 2.0
Name: phlib
Version: 0.1.1
Summary: A PornHub client.
Home-page: https://github.com/kennethreitz/phlib
Author: Kenneth Reitz
Author-email: me@kennethreitz.org
License: MIT
Platform: UNKNOWN
Classifier: License :: OSI Approved :: MIT License
Classifier: Programming Language :: Python
Classifier: Programming Language :: Python :: 3
Classifier: Programming Language :: Python :: 3.3
Classifier: Programming Language :: Python :: 3.4
Classifier: Programming Language :: Python :: 3.5
Classifier: Programming Language :: Python :: 3.6
Classifier: Programming Language :: Python :: Implementation :: CPython
Classifier: Programming Language :: Python :: Implementation :: PyPy
Requires-Dist: requests
Requires-Dist: bs4
Requires-Dist: delegator.py
Requires-Dist: crayons
Requires-Dist: docopt
Requires-Dist: youtube-dl
Requires-Dist: lxml
